diblob/__init__.py
diblob/algorithms.py
diblob/components.py
diblob/digraph_manager.py
diblob/exceptions.py
diblob/factory.py
diblob/generators.py
diblob/tools.py
diblob-2.1.4.dist-info/licenses/LICENCE.txt
testing_criterions/AcyclicPathCoverage.py
testing_criterions/CPT.py
testing_criterions/CPTTestCasesGenerator.py
testing_criterions/EdgeCoverage.py
testing_criterions/NSwitchCoverage.py
testing_criterions/NodeCoverage.py
testing_criterions/PrimePathCoverage.py
testing_criterions/SimpleCycleCoverage.py
testing_criterions/SimplePathsCoverage.py
testing_criterions/__init__.py
testing_criterions/decorators.py
testing_criterions/exceptions.py
diblob-2.1.4.dist-info/METADATA
diblob-2.1.4.dist-info/WHEEL
diblob-2.1.4.dist-info/top_level.txt
diblob-2.1.4.dist-info/RECORD
