Metadata-Version: 2.4
Name: diblob
Version: 2.1.4
Summary: Diblob is a lightweight Python package for test case coverage of directed graphs (digraphs), with a focus on SESE graphs (Single Entry, Single Exit — graphs with one source and one sink). It is primarily developed for testing purposes and provides a simple, dependency-free solution built entirely on standard Python data structures.
Home-page: https://github.com/JakubZelek/Diblob
Author: Jakub Zelek
Author-email: jakub.zelek@doctoral.uj.edu.pl
License: MIT
Classifier: Programming Language :: Python :: 3.10
Classifier: License :: OSI Approved :: MIT License
Classifier: Operating System :: OS Independent
Requires-Python: >=3.10
License-File: LICENCE.txt
Dynamic: author
Dynamic: author-email
Dynamic: classifier
Dynamic: description
Dynamic: description-content-type
Dynamic: home-page
Dynamic: license
Dynamic: license-file
Dynamic: requires-python
Dynamic: summary
